flox_sentry/__init__.py
flox_sentry/configure.py
flox_sentry/project.py
flox_sentry/sentry.py
flox_sentry-0.1.4.dist-info/entry_points.txt
flox_sentry-0.1.4.dist-info/LICENSE
flox_sentry-0.1.4.dist-info/WHEEL
flox_sentry-0.1.4.dist-info/METADATA
flox_sentry-0.1.4.dist-info/RECORD
