Metadata-Version: 2.1
Name: flox-sentry
Version: 0.1.4
Summary: Automatically create projects and teams for flox managed projects
Home-page: https://github.com/getflox/flox-sentry
License: MIT
Author: Michal Przytulski
Author-email: michal@przytulski.pl
Requires-Python: >=3.6.2,<4.0.0
Classifier: License :: OSI Approved :: MIT License
Classifier: Programming Language :: Python :: 3
Classifier: Programming Language :: Python :: 3.7
Classifier: Programming Language :: Python :: 3.8
Requires-Dist: flox-core (>=0.2,<1.0.0)
Requires-Dist: python-slugify (>=4.0,<5.0)
Requires-Dist: requests-toolbelt (>=0.9,<0.10)
